pybitfsm/__init__.py
pybitfsm/bits.py
pybitfsm/c_api.py
pybitfsm/formatters.py
pybitfsm/libbitfsmopt.so
pybitfsm/libname.py
pybitfsm/optimizer.py
pybitfsm/types.py
pybitfsm-0.0.1.dist-info/METADATA
pybitfsm-0.0.1.dist-info/WHEEL
pybitfsm-0.0.1.dist-info/RECORD
pybitfsm-0.0.1.dist-info/licenses/LICENSE.txt
pybitfsm-0.0.1.dist-info/licenses/third_party/doctest/LICENSE.txt
pybitfsm-0.0.1.dist-info/licenses/third_party/taskflow/LICENSE.txt
pybitfsm-0.0.1.dist-info/licenses/third_party/wyhash/LICENSE.txt
pybitfsm-0.0.1.dist-info/licenses/third_party/xoshiro256pp/LICENSE.txt
pybitfsm-0.0.1.dist-info/licenses/third_party/xxhash/LICENSE.txt
